LICENSE
MANIFEST.in
README
requirements.txt
setup.cfg
setup.py
src/nriapp/nriapp.egg-info/PKG-INFO
src/nriapp/nriapp.egg-info/SOURCES.txt
src/nriapp/nriapp.egg-info/dependency_links.txt
src/nriapp/nriapp.egg-info/entry_points.txt
src/nriapp/nriapp.egg-info/top_level.txt
src/nriapp/__init__.py
src/nriapp/changelog.txt
src/nriapp/nriapp.py
src/nriapp/config/__init__.py
src/nriapp/config/config.py
src/nriapp/core/__init__.py
src/nriapp/core/abuseipdbapi.py
src/nriapp/core/dataexplorer.py
src/nriapp/core/msgraphapi.py
src/nriapp/core/mssentinelapi.py
src/nriapp/core/multifactor.py
src/nriapp/core/vtquery.py
src/nriapp/helper/__init__.py
src/nriapp/helper/doc.py
src/nriapp/helper/excel.py
src/nriapp/helper/login.py
src/nriapp/helper/pylog.py
src/nriapp/helper/requestheader.py
src/nriapp/helper/visualization.py
src/nriapp/nriapp.egg-info/PKG-INFO
src/nriapp/nriapp.egg-info/SOURCES.txt
src/nriapp/nriapp.egg-info/dependency_links.txt
src/nriapp/nriapp.egg-info/entry_points.txt
src/nriapp/nriapp.egg-info/top_level.txt