Metadata-Version: 1.0
Name: nriapp
Version: 1.1.10
Summary: This is an internal tool for crawling MS 365 Defender web with NRI
Home-page: UNKNOWN
Author: Llallum Victoria
Author-email: llallumvictoria@gmail.com
License: MIT
Platform: UNKNOWN
